[
  [
    "93ee02aeb480abd5",
    {
      "hashCode": "93ee02aeb480abd5",
      "data": {
        "id": "Fc5MWVrvDObdx5Hvt",
        "actId": "oAuCIx3ItNrs2okjQ",
        "stats": {
          "inputBodyLen": 452,
          "migrationCount": 0,
          "rebootCount": 0,
          "restartCount": 0,
          "resurrectCount": 0,
          "computeUnits": 0
        },
        "defaultKeyValueStoreId": "ecVlMMtResMPgBTI5",
        "defaultDatasetId": "janbxteH1CrJHYkTF",
        "defaultRequestQueueId": "KfK5NdUZR6hQSBuFl",
        "pricingInfo": {
          "pricingModel": "PAY_PER_EVENT",
          "reasonForChange": "We are switching to Pay Per Event for a better pricing for our customers.",
          "startedAt": "2025-02-20T00:00:00.000Z",
          "minimalMaxTotalChargeUsd": null,
          "createdAt": "2025-02-13T10:52:56.554Z",
          "apifyMarginPercentage": 0.2,
          "notifiedAboutFutureChangeAt": "2025-02-13T10:53:21.733Z",
          "notifiedAboutChangeAt": "2025-02-20T02:39:19.462Z",
          "pricingPerEvent": {
            "actorChargeEvents": {
              "actor-start-gb": {
                "eventTitle": "Actor start per 1 GB",
                "eventDescription": "Flat fee for starting an Actor run for each 1 GB of memory.",
                "eventPriceUsd": 0.02
              },
              "result": {
                "eventTitle": "Result stored",
                "eventDescription": "Cost per result stored.",
                "eventPriceUsd": 0.004
              }
            }
          }
        },
        "chargedEventCounts": {
          "actor-start-gb": 0,
          "result": 0
        },
        "platformUsageBillingModel": "USER",
        "accountedChargedEventCounts": {
          "actor-start-gb": 0,
          "result": 0
        },
        "generalAccess": "FOLLOW_USER_SETTING",
        "buildNumber": "4.17.41",
        "usage": {
          "ACTOR_COMPUTE_UNITS": 0,
          "DATASET_READS": 0,
          "DATASET_WRITES": 0,
          "KEY_VALUE_STORE_READS": 0,
          "KEY_VALUE_STORE_WRITES": 1,
          "KEY_VALUE_STORE_LISTS": 0,
          "REQUEST_QUEUE_READS": 0,
          "REQUEST_QUEUE_WRITES": 0,
          "DATA_TRANSFER_INTERNAL_GBYTES": 0,
          "DATA_TRANSFER_EXTERNAL_GBYTES": 0,
          "PROXY_RESIDENTIAL_TRANSFER_GBYTES": 0,
          "PROXY_SERPS": 0
        },
        "usageTotalUsd": 0.00005,
        "usageUsd": {
          "ACTOR_COMPUTE_UNITS": 0,
          "DATASET_READS": 0,
          "DATASET_WRITES": 0,
          "KEY_VALUE_STORE_READS": 0,
          "KEY_VALUE_STORE_WRITES": 0.00005,
          "KEY_VALUE_STORE_LISTS": 0,
          "REQUEST_QUEUE_READS": 0,
          "REQUEST_QUEUE_WRITES": 0,
          "DATA_TRANSFER_INTERNAL_GBYTES": 0,
          "DATA_TRANSFER_EXTERNAL_GBYTES": 0,
          "PROXY_RESIDENTIAL_TRANSFER_GBYTES": 0,
          "PROXY_SERPS": 0
        },
        "consoleUrl": "https://console.apify.com/view/runs/Fc5MWVrvDObdx5Hvt",
        "actorName": "reddit-scraper-lite",
        "name": "Reddit Search Post Health Check"
      },
      "runId": "Fc5MWVrvDObdx5Hvt"
    }
  ],
  [
    "6bb31dc9561a1c87",
    {
      "hashCode": "6bb31dc9561a1c87",
      "data": {
        "id": "T80OeWs4pEjTQzED5",
        "actId": "oAuCIx3ItNrs2okjQ",
        "stats": {
          "inputBodyLen": 552,
          "migrationCount": 0,
          "rebootCount": 0,
          "restartCount": 0,
          "resurrectCount": 0,
          "computeUnits": 0
        },
        "defaultKeyValueStoreId": "qqtJFtrorXHzXUfZo",
        "defaultDatasetId": "b5S3BixScUOGCgZ7b",
        "defaultRequestQueueId": "ZbAfRAO6S8Z1sq9tc",
        "pricingInfo": {
          "pricingModel": "PAY_PER_EVENT",
          "reasonForChange": "We are switching to Pay Per Event for a better pricing for our customers.",
          "startedAt": "2025-02-20T00:00:00.000Z",
          "minimalMaxTotalChargeUsd": null,
          "createdAt": "2025-02-13T10:52:56.554Z",
          "apifyMarginPercentage": 0.2,
          "notifiedAboutFutureChangeAt": "2025-02-13T10:53:21.733Z",
          "notifiedAboutChangeAt": "2025-02-20T02:39:19.462Z",
          "pricingPerEvent": {
            "actorChargeEvents": {
              "actor-start-gb": {
                "eventTitle": "Actor start per 1 GB",
                "eventDescription": "Flat fee for starting an Actor run for each 1 GB of memory.",
                "eventPriceUsd": 0.02
              },
              "result": {
                "eventTitle": "Result stored",
                "eventDescription": "Cost per result stored.",
                "eventPriceUsd": 0.004
              }
            }
          }
        },
        "chargedEventCounts": {
          "actor-start-gb": 0,
          "result": 0
        },
        "platformUsageBillingModel": "USER",
        "accountedChargedEventCounts": {
          "actor-start-gb": 0,
          "result": 0
        },
        "generalAccess": "FOLLOW_USER_SETTING",
        "buildNumber": "4.17.41",
        "usage": {
          "ACTOR_COMPUTE_UNITS": 0,
          "DATASET_READS": 0,
          "DATASET_WRITES": 0,
          "KEY_VALUE_STORE_READS": 0,
          "KEY_VALUE_STORE_WRITES": 1,
          "KEY_VALUE_STORE_LISTS": 0,
          "REQUEST_QUEUE_READS": 0,
          "REQUEST_QUEUE_WRITES": 0,
          "DATA_TRANSFER_INTERNAL_GBYTES": 0,
          "DATA_TRANSFER_EXTERNAL_GBYTES": 0,
          "PROXY_RESIDENTIAL_TRANSFER_GBYTES": 0,
          "PROXY_SERPS": 0
        },
        "usageTotalUsd": 0.00005,
        "usageUsd": {
          "ACTOR_COMPUTE_UNITS": 0,
          "DATASET_READS": 0,
          "DATASET_WRITES": 0,
          "KEY_VALUE_STORE_READS": 0,
          "KEY_VALUE_STORE_WRITES": 0.00005,
          "KEY_VALUE_STORE_LISTS": 0,
          "REQUEST_QUEUE_READS": 0,
          "REQUEST_QUEUE_WRITES": 0,
          "DATA_TRANSFER_INTERNAL_GBYTES": 0,
          "DATA_TRANSFER_EXTERNAL_GBYTES": 0,
          "PROXY_RESIDENTIAL_TRANSFER_GBYTES": 0,
          "PROXY_SERPS": 0
        },
        "consoleUrl": "https://console.apify.com/view/runs/T80OeWs4pEjTQzED5",
        "actorName": "reddit-scraper-lite",
        "name": "Reddit PRO Search Post Start Url Health Check"
      },
      "runId": "T80OeWs4pEjTQzED5"
    }
  ],
  [
    "e57b6833079bf415",
    {
      "hashCode": "e57b6833079bf415",
      "data": {
        "id": "9D1GDDbMA0vFO5Bv9",
        "actId": "oAuCIx3ItNrs2okjQ",
        "stats": {
          "inputBodyLen": 530,
          "migrationCount": 0,
          "rebootCount": 0,
          "restartCount": 0,
          "resurrectCount": 0,
          "computeUnits": 0
        },
        "defaultKeyValueStoreId": "Gzx3TLI0rmADWwqml",
        "defaultDatasetId": "Amfr3E1FZBmW4edqF",
        "defaultRequestQueueId": "UwZhiLIa1eCsabba6",
        "pricingInfo": {
          "pricingModel": "PAY_PER_EVENT",
          "reasonForChange": "We are switching to Pay Per Event for a better pricing for our customers.",
          "startedAt": "2025-02-20T00:00:00.000Z",
          "minimalMaxTotalChargeUsd": null,
          "createdAt": "2025-02-13T10:52:56.554Z",
          "apifyMarginPercentage": 0.2,
          "notifiedAboutFutureChangeAt": "2025-02-13T10:53:21.733Z",
          "notifiedAboutChangeAt": "2025-02-20T02:39:19.462Z",
          "pricingPerEvent": {
            "actorChargeEvents": {
              "actor-start-gb": {
                "eventTitle": "Actor start per 1 GB",
                "eventDescription": "Flat fee for starting an Actor run for each 1 GB of memory.",
                "eventPriceUsd": 0.02
              },
              "result": {
                "eventTitle": "Result stored",
                "eventDescription": "Cost per result stored.",
                "eventPriceUsd": 0.004
              }
            }
          }
        },
        "chargedEventCounts": {
          "actor-start-gb": 0,
          "result": 0
        },
        "platformUsageBillingModel": "USER",
        "accountedChargedEventCounts": {
          "actor-start-gb": 0,
          "result": 0
        },
        "generalAccess": "FOLLOW_USER_SETTING",
        "buildNumber": "4.17.41",
        "usage": {
          "ACTOR_COMPUTE_UNITS": 0,
          "DATASET_READS": 0,
          "DATASET_WRITES": 0,
          "KEY_VALUE_STORE_READS": 0,
          "KEY_VALUE_STORE_WRITES": 1,
          "KEY_VALUE_STORE_LISTS": 0,
          "REQUEST_QUEUE_READS": 0,
          "REQUEST_QUEUE_WRITES": 0,
          "DATA_TRANSFER_INTERNAL_GBYTES": 0,
          "DATA_TRANSFER_EXTERNAL_GBYTES": 0,
          "PROXY_RESIDENTIAL_TRANSFER_GBYTES": 0,
          "PROXY_SERPS": 0
        },
        "usageTotalUsd": 0.00005,
        "usageUsd": {
          "ACTOR_COMPUTE_UNITS": 0,
          "DATASET_READS": 0,
          "DATASET_WRITES": 0,
          "KEY_VALUE_STORE_READS": 0,
          "KEY_VALUE_STORE_WRITES": 0.00005,
          "KEY_VALUE_STORE_LISTS": 0,
          "REQUEST_QUEUE_READS": 0,
          "REQUEST_QUEUE_WRITES": 0,
          "DATA_TRANSFER_INTERNAL_GBYTES": 0,
          "DATA_TRANSFER_EXTERNAL_GBYTES": 0,
          "PROXY_RESIDENTIAL_TRANSFER_GBYTES": 0,
          "PROXY_SERPS": 0
        },
        "consoleUrl": "https://console.apify.com/view/runs/9D1GDDbMA0vFO5Bv9",
        "actorName": "reddit-scraper-lite",
        "name": "Reddit Search Post Start Url Health Check"
      },
      "runId": "9D1GDDbMA0vFO5Bv9"
    }
  ],
  [
    "bbc8fc9cabf24f34",
    {
      "hashCode": "bbc8fc9cabf24f34",
      "data": {
        "id": "lahmoayCN5UcLykkX",
        "actId": "oAuCIx3ItNrs2okjQ",
        "stats": {
          "inputBodyLen": 452,
          "migrationCount": 0,
          "rebootCount": 0,
          "restartCount": 0,
          "resurrectCount": 0,
          "computeUnits": 0
        },
        "defaultKeyValueStoreId": "daWNDs7gWZGFqaNQh",
        "defaultDatasetId": "xmi88TiJ629wuVSrk",
        "defaultRequestQueueId": "pQdNapphy1UXoWkwN",
        "pricingInfo": {
          "pricingModel": "PAY_PER_EVENT",
          "reasonForChange": "We are switching to Pay Per Event for a better pricing for our customers.",
          "startedAt": "2025-02-20T00:00:00.000Z",
          "minimalMaxTotalChargeUsd": null,
          "createdAt": "2025-02-13T10:52:56.554Z",
          "apifyMarginPercentage": 0.2,
          "notifiedAboutFutureChangeAt": "2025-02-13T10:53:21.733Z",
          "notifiedAboutChangeAt": "2025-02-20T02:39:19.462Z",
          "pricingPerEvent": {
            "actorChargeEvents": {
              "actor-start-gb": {
                "eventTitle": "Actor start per 1 GB",
                "eventDescription": "Flat fee for starting an Actor run for each 1 GB of memory.",
                "eventPriceUsd": 0.02
              },
              "result": {
                "eventTitle": "Result stored",
                "eventDescription": "Cost per result stored.",
                "eventPriceUsd": 0.004
              }
            }
          }
        },
        "chargedEventCounts": {
          "actor-start-gb": 0,
          "result": 0
        },
        "platformUsageBillingModel": "USER",
        "accountedChargedEventCounts": {
          "actor-start-gb": 0,
          "result": 0
        },
        "generalAccess": "FOLLOW_USER_SETTING",
        "buildNumber": "4.17.41",
        "usage": {
          "ACTOR_COMPUTE_UNITS": 0,
          "DATASET_READS": 0,
          "DATASET_WRITES": 0,
          "KEY_VALUE_STORE_READS": 0,
          "KEY_VALUE_STORE_WRITES": 1,
          "KEY_VALUE_STORE_LISTS": 0,
          "REQUEST_QUEUE_READS": 0,
          "REQUEST_QUEUE_WRITES": 0,
          "DATA_TRANSFER_INTERNAL_GBYTES": 0,
          "DATA_TRANSFER_EXTERNAL_GBYTES": 0,
          "PROXY_RESIDENTIAL_TRANSFER_GBYTES": 0,
          "PROXY_SERPS": 0
        },
        "usageTotalUsd": 0.00005,
        "usageUsd": {
          "ACTOR_COMPUTE_UNITS": 0,
          "DATASET_READS": 0,
          "DATASET_WRITES": 0,
          "KEY_VALUE_STORE_READS": 0,
          "KEY_VALUE_STORE_WRITES": 0.00005,
          "KEY_VALUE_STORE_LISTS": 0,
          "REQUEST_QUEUE_READS": 0,
          "REQUEST_QUEUE_WRITES": 0,
          "DATA_TRANSFER_INTERNAL_GBYTES": 0,
          "DATA_TRANSFER_EXTERNAL_GBYTES": 0,
          "PROXY_RESIDENTIAL_TRANSFER_GBYTES": 0,
          "PROXY_SERPS": 0
        },
        "consoleUrl": "https://console.apify.com/view/runs/lahmoayCN5UcLykkX",
        "actorName": "reddit-scraper-lite",
        "name": "Reddit Search Comments Health Check"
      },
      "runId": "lahmoayCN5UcLykkX"
    }
  ],
  [
    "1e2e6694dd308296",
    {
      "hashCode": "1e2e6694dd308296",
      "data": {
        "id": "0eRjuqMO9cdIH0rcc",
        "actId": "oAuCIx3ItNrs2okjQ",
        "stats": {
          "inputBodyLen": 452,
          "migrationCount": 0,
          "rebootCount": 0,
          "restartCount": 0,
          "resurrectCount": 0,
          "computeUnits": 0
        },
        "defaultKeyValueStoreId": "IMxYygXafAiJSMK5Z",
        "defaultDatasetId": "aCbaJEkDHT0cd7kWm",
        "defaultRequestQueueId": "zTeETSGQCUXueaAxg",
        "pricingInfo": {
          "pricingModel": "PAY_PER_EVENT",
          "reasonForChange": "We are switching to Pay Per Event for a better pricing for our customers.",
          "startedAt": "2025-02-20T00:00:00.000Z",
          "minimalMaxTotalChargeUsd": null,
          "createdAt": "2025-02-13T10:52:56.554Z",
          "apifyMarginPercentage": 0.2,
          "notifiedAboutFutureChangeAt": "2025-02-13T10:53:21.733Z",
          "notifiedAboutChangeAt": "2025-02-20T02:39:19.462Z",
          "pricingPerEvent": {
            "actorChargeEvents": {
              "actor-start-gb": {
                "eventTitle": "Actor start per 1 GB",
                "eventDescription": "Flat fee for starting an Actor run for each 1 GB of memory.",
                "eventPriceUsd": 0.02
              },
              "result": {
                "eventTitle": "Result stored",
                "eventDescription": "Cost per result stored.",
                "eventPriceUsd": 0.004
              }
            }
          }
        },
        "chargedEventCounts": {
          "actor-start-gb": 0,
          "result": 0
        },
        "platformUsageBillingModel": "USER",
        "accountedChargedEventCounts": {
          "actor-start-gb": 0,
          "result": 0
        },
        "generalAccess": "FOLLOW_USER_SETTING",
        "buildNumber": "4.17.41",
        "usage": {
          "ACTOR_COMPUTE_UNITS": 0,
          "DATASET_READS": 0,
          "DATASET_WRITES": 0,
          "KEY_VALUE_STORE_READS": 0,
          "KEY_VALUE_STORE_WRITES": 1,
          "KEY_VALUE_STORE_LISTS": 0,
          "REQUEST_QUEUE_READS": 0,
          "REQUEST_QUEUE_WRITES": 0,
          "DATA_TRANSFER_INTERNAL_GBYTES": 0,
          "DATA_TRANSFER_EXTERNAL_GBYTES": 0,
          "PROXY_RESIDENTIAL_TRANSFER_GBYTES": 0,
          "PROXY_SERPS": 0
        },
        "usageTotalUsd": 0.00005,
        "usageUsd": {
          "ACTOR_COMPUTE_UNITS": 0,
          "DATASET_READS": 0,
          "DATASET_WRITES": 0,
          "KEY_VALUE_STORE_READS": 0,
          "KEY_VALUE_STORE_WRITES": 0.00005,
          "KEY_VALUE_STORE_LISTS": 0,
          "REQUEST_QUEUE_READS": 0,
          "REQUEST_QUEUE_WRITES": 0,
          "DATA_TRANSFER_INTERNAL_GBYTES": 0,
          "DATA_TRANSFER_EXTERNAL_GBYTES": 0,
          "PROXY_RESIDENTIAL_TRANSFER_GBYTES": 0,
          "PROXY_SERPS": 0
        },
        "consoleUrl": "https://console.apify.com/view/runs/0eRjuqMO9cdIH0rcc",
        "actorName": "reddit-scraper-lite",
        "name": "Reddit Search Users Health Check"
      },
      "runId": "0eRjuqMO9cdIH0rcc"
    }
  ],
  [
    "625655f0ab01ee2c",
    {
      "hashCode": "625655f0ab01ee2c",
      "data": {
        "id": "yOIqx7o8rvxC7yxNP",
        "actId": "oAuCIx3ItNrs2okjQ",
        "stats": {
          "inputBodyLen": 445,
          "migrationCount": 0,
          "rebootCount": 0,
          "restartCount": 0,
          "resurrectCount": 0,
          "computeUnits": 0
        },
        "defaultKeyValueStoreId": "xAQ6L1DAhwtfLFncg",
        "defaultDatasetId": "Jt4rfKBvErby1aLcy",
        "defaultRequestQueueId": "Zbl45biICUQNxBKrN",
        "pricingInfo": {
          "pricingModel": "PAY_PER_EVENT",
          "reasonForChange": "We are switching to Pay Per Event for a better pricing for our customers.",
          "startedAt": "2025-02-20T00:00:00.000Z",
          "minimalMaxTotalChargeUsd": null,
          "createdAt": "2025-02-13T10:52:56.554Z",
          "apifyMarginPercentage": 0.2,
          "notifiedAboutFutureChangeAt": "2025-02-13T10:53:21.733Z",
          "notifiedAboutChangeAt": "2025-02-20T02:39:19.462Z",
          "pricingPerEvent": {
            "actorChargeEvents": {
              "actor-start-gb": {
                "eventTitle": "Actor start per 1 GB",
                "eventDescription": "Flat fee for starting an Actor run for each 1 GB of memory.",
                "eventPriceUsd": 0.02
              },
              "result": {
                "eventTitle": "Result stored",
                "eventDescription": "Cost per result stored.",
                "eventPriceUsd": 0.004
              }
            }
          }
        },
        "chargedEventCounts": {
          "actor-start-gb": 0,
          "result": 0
        },
        "platformUsageBillingModel": "USER",
        "accountedChargedEventCounts": {
          "actor-start-gb": 0,
          "result": 0
        },
        "generalAccess": "FOLLOW_USER_SETTING",
        "buildNumber": "4.17.41",
        "usage": {
          "ACTOR_COMPUTE_UNITS": 0,
          "DATASET_READS": 0,
          "DATASET_WRITES": 0,
          "KEY_VALUE_STORE_READS": 0,
          "KEY_VALUE_STORE_WRITES": 1,
          "KEY_VALUE_STORE_LISTS": 0,
          "REQUEST_QUEUE_READS": 0,
          "REQUEST_QUEUE_WRITES": 0,
          "DATA_TRANSFER_INTERNAL_GBYTES": 0,
          "DATA_TRANSFER_EXTERNAL_GBYTES": 0,
          "PROXY_RESIDENTIAL_TRANSFER_GBYTES": 0,
          "PROXY_SERPS": 0
        },
        "usageTotalUsd": 0.00005,
        "usageUsd": {
          "ACTOR_COMPUTE_UNITS": 0,
          "DATASET_READS": 0,
          "DATASET_WRITES": 0,
          "KEY_VALUE_STORE_READS": 0,
          "KEY_VALUE_STORE_WRITES": 0.00005,
          "KEY_VALUE_STORE_LISTS": 0,
          "REQUEST_QUEUE_READS": 0,
          "REQUEST_QUEUE_WRITES": 0,
          "DATA_TRANSFER_INTERNAL_GBYTES": 0,
          "DATA_TRANSFER_EXTERNAL_GBYTES": 0,
          "PROXY_RESIDENTIAL_TRANSFER_GBYTES": 0,
          "PROXY_SERPS": 0
        },
        "consoleUrl": "https://console.apify.com/view/runs/yOIqx7o8rvxC7yxNP",
        "actorName": "reddit-scraper-lite",
        "name": "Reddit Search Community Check"
      },
      "runId": "yOIqx7o8rvxC7yxNP"
    }
  ],
  [
    "30f5c54aaadc286b",
    {
      "hashCode": "30f5c54aaadc286b",
      "data": {
        "id": "ohT1hmIdM1WovuOvt",
        "actId": "oAuCIx3ItNrs2okjQ",
        "stats": {
          "inputBodyLen": 466,
          "migrationCount": 0,
          "rebootCount": 0,
          "restartCount": 0,
          "resurrectCount": 0,
          "computeUnits": 0
        },
        "defaultKeyValueStoreId": "zqvogcRIOHO2Trvds",
        "defaultDatasetId": "qYGNbidM4alM2d7hx",
        "defaultRequestQueueId": "gXxAFhGzgxqCSUYKU",
        "pricingInfo": {
          "pricingModel": "PAY_PER_EVENT",
          "reasonForChange": "We are switching to Pay Per Event for a better pricing for our customers.",
          "startedAt": "2025-02-20T00:00:00.000Z",
          "minimalMaxTotalChargeUsd": null,
          "createdAt": "2025-02-13T10:52:56.554Z",
          "apifyMarginPercentage": 0.2,
          "notifiedAboutFutureChangeAt": "2025-02-13T10:53:21.733Z",
          "notifiedAboutChangeAt": "2025-02-20T02:39:19.462Z",
          "pricingPerEvent": {
            "actorChargeEvents": {
              "actor-start-gb": {
                "eventTitle": "Actor start per 1 GB",
                "eventDescription": "Flat fee for starting an Actor run for each 1 GB of memory.",
                "eventPriceUsd": 0.02
              },
              "result": {
                "eventTitle": "Result stored",
                "eventDescription": "Cost per result stored.",
                "eventPriceUsd": 0.004
              }
            }
          }
        },
        "chargedEventCounts": {
          "actor-start-gb": 0,
          "result": 0
        },
        "platformUsageBillingModel": "USER",
        "accountedChargedEventCounts": {
          "actor-start-gb": 0,
          "result": 0
        },
        "generalAccess": "FOLLOW_USER_SETTING",
        "buildNumber": "4.17.41",
        "usage": {
          "ACTOR_COMPUTE_UNITS": 0,
          "DATASET_READS": 0,
          "DATASET_WRITES": 0,
          "KEY_VALUE_STORE_READS": 0,
          "KEY_VALUE_STORE_WRITES": 1,
          "KEY_VALUE_STORE_LISTS": 0,
          "REQUEST_QUEUE_READS": 0,
          "REQUEST_QUEUE_WRITES": 0,
          "DATA_TRANSFER_INTERNAL_GBYTES": 0,
          "DATA_TRANSFER_EXTERNAL_GBYTES": 0,
          "PROXY_RESIDENTIAL_TRANSFER_GBYTES": 0,
          "PROXY_SERPS": 0
        },
        "usageTotalUsd": 0.00005,
        "usageUsd": {
          "ACTOR_COMPUTE_UNITS": 0,
          "DATASET_READS": 0,
          "DATASET_WRITES": 0,
          "KEY_VALUE_STORE_READS": 0,
          "KEY_VALUE_STORE_WRITES": 0.00005,
          "KEY_VALUE_STORE_LISTS": 0,
          "REQUEST_QUEUE_READS": 0,
          "REQUEST_QUEUE_WRITES": 0,
          "DATA_TRANSFER_INTERNAL_GBYTES": 0,
          "DATA_TRANSFER_EXTERNAL_GBYTES": 0,
          "PROXY_RESIDENTIAL_TRANSFER_GBYTES": 0,
          "PROXY_SERPS": 0
        },
        "consoleUrl": "https://console.apify.com/view/runs/ohT1hmIdM1WovuOvt",
        "actorName": "reddit-scraper-lite",
        "name": "Reddit Pro Search Community Check"
      },
      "runId": "ohT1hmIdM1WovuOvt"
    }
  ],
  [
    "85984aa435b91c03",
    {
      "hashCode": "85984aa435b91c03",
      "data": {
        "id": "PTfRv1gZfxYHfZSim",
        "actId": "oAuCIx3ItNrs2okjQ",
        "stats": {
          "inputBodyLen": 484,
          "migrationCount": 0,
          "rebootCount": 0,
          "restartCount": 0,
          "resurrectCount": 0,
          "computeUnits": 0
        },
        "defaultKeyValueStoreId": "TFTbIFSwOIVq9Ga1x",
        "defaultDatasetId": "864jWbPZ4FZs7QEwG",
        "defaultRequestQueueId": "8Wj5IJK0MyvOl9gCQ",
        "pricingInfo": {
          "pricingModel": "PAY_PER_EVENT",
          "reasonForChange": "We are switching to Pay Per Event for a better pricing for our customers.",
          "startedAt": "2025-02-20T00:00:00.000Z",
          "minimalMaxTotalChargeUsd": null,
          "createdAt": "2025-02-13T10:52:56.554Z",
          "apifyMarginPercentage": 0.2,
          "notifiedAboutFutureChangeAt": "2025-02-13T10:53:21.733Z",
          "notifiedAboutChangeAt": "2025-02-20T02:39:19.462Z",
          "pricingPerEvent": {
            "actorChargeEvents": {
              "actor-start-gb": {
                "eventTitle": "Actor start per 1 GB",
                "eventDescription": "Flat fee for starting an Actor run for each 1 GB of memory.",
                "eventPriceUsd": 0.02
              },
              "result": {
                "eventTitle": "Result stored",
                "eventDescription": "Cost per result stored.",
                "eventPriceUsd": 0.004
              }
            }
          }
        },
        "chargedEventCounts": {
          "actor-start-gb": 0,
          "result": 0
        },
        "platformUsageBillingModel": "USER",
        "accountedChargedEventCounts": {
          "actor-start-gb": 0,
          "result": 0
        },
        "generalAccess": "FOLLOW_USER_SETTING",
        "buildNumber": "4.17.41",
        "usage": {
          "ACTOR_COMPUTE_UNITS": 0,
          "DATASET_READS": 0,
          "DATASET_WRITES": 0,
          "KEY_VALUE_STORE_READS": 0,
          "KEY_VALUE_STORE_WRITES": 1,
          "KEY_VALUE_STORE_LISTS": 0,
          "REQUEST_QUEUE_READS": 0,
          "REQUEST_QUEUE_WRITES": 0,
          "DATA_TRANSFER_INTERNAL_GBYTES": 0,
          "DATA_TRANSFER_EXTERNAL_GBYTES": 0,
          "PROXY_RESIDENTIAL_TRANSFER_GBYTES": 0,
          "PROXY_SERPS": 0
        },
        "usageTotalUsd": 0.00005,
        "usageUsd": {
          "ACTOR_COMPUTE_UNITS": 0,
          "DATASET_READS": 0,
          "DATASET_WRITES": 0,
          "KEY_VALUE_STORE_READS": 0,
          "KEY_VALUE_STORE_WRITES": 0.00005,
          "KEY_VALUE_STORE_LISTS": 0,
          "REQUEST_QUEUE_READS": 0,
          "REQUEST_QUEUE_WRITES": 0,
          "DATA_TRANSFER_INTERNAL_GBYTES": 0,
          "DATA_TRANSFER_EXTERNAL_GBYTES": 0,
          "PROXY_RESIDENTIAL_TRANSFER_GBYTES": 0,
          "PROXY_SERPS": 0
        },
        "consoleUrl": "https://console.apify.com/view/runs/PTfRv1gZfxYHfZSim",
        "actorName": "reddit-scraper-lite",
        "name": "Reddit Community Check"
      },
      "runId": "PTfRv1gZfxYHfZSim"
    }
  ],
  [
    "4341a07512c43398",
    {
      "hashCode": "4341a07512c43398",
      "data": {
        "id": "dHGEPuVi9e5c9opK5",
        "actId": "oAuCIx3ItNrs2okjQ",
        "stats": {
          "inputBodyLen": 479,
          "migrationCount": 0,
          "rebootCount": 0,
          "restartCount": 0,
          "resurrectCount": 0,
          "computeUnits": 0
        },
        "defaultKeyValueStoreId": "c9oC2J1B7mwz54aYm",
        "defaultDatasetId": "mQP0YEOvgsPR7wQx2",
        "defaultRequestQueueId": "PuuBZV7dEvg7qqyUy",
        "pricingInfo": {
          "pricingModel": "PAY_PER_EVENT",
          "reasonForChange": "We are switching to Pay Per Event for a better pricing for our customers.",
          "startedAt": "2025-02-20T00:00:00.000Z",
          "minimalMaxTotalChargeUsd": null,
          "createdAt": "2025-02-13T10:52:56.554Z",
          "apifyMarginPercentage": 0.2,
          "notifiedAboutFutureChangeAt": "2025-02-13T10:53:21.733Z",
          "notifiedAboutChangeAt": "2025-02-20T02:39:19.462Z",
          "pricingPerEvent": {
            "actorChargeEvents": {
              "actor-start-gb": {
                "eventTitle": "Actor start per 1 GB",
                "eventDescription": "Flat fee for starting an Actor run for each 1 GB of memory.",
                "eventPriceUsd": 0.02
              },
              "result": {
                "eventTitle": "Result stored",
                "eventDescription": "Cost per result stored.",
                "eventPriceUsd": 0.004
              }
            }
          }
        },
        "chargedEventCounts": {
          "actor-start-gb": 0,
          "result": 0
        },
        "platformUsageBillingModel": "USER",
        "accountedChargedEventCounts": {
          "actor-start-gb": 0,
          "result": 0
        },
        "generalAccess": "FOLLOW_USER_SETTING",
        "buildNumber": "4.17.41",
        "usage": {
          "ACTOR_COMPUTE_UNITS": 0,
          "DATASET_READS": 0,
          "DATASET_WRITES": 0,
          "KEY_VALUE_STORE_READS": 0,
          "KEY_VALUE_STORE_WRITES": 1,
          "KEY_VALUE_STORE_LISTS": 0,
          "REQUEST_QUEUE_READS": 0,
          "REQUEST_QUEUE_WRITES": 0,
          "DATA_TRANSFER_INTERNAL_GBYTES": 0,
          "DATA_TRANSFER_EXTERNAL_GBYTES": 0,
          "PROXY_RESIDENTIAL_TRANSFER_GBYTES": 0,
          "PROXY_SERPS": 0
        },
        "usageTotalUsd": 0.00005,
        "usageUsd": {
          "ACTOR_COMPUTE_UNITS": 0,
          "DATASET_READS": 0,
          "DATASET_WRITES": 0,
          "KEY_VALUE_STORE_READS": 0,
          "KEY_VALUE_STORE_WRITES": 0.00005,
          "KEY_VALUE_STORE_LISTS": 0,
          "REQUEST_QUEUE_READS": 0,
          "REQUEST_QUEUE_WRITES": 0,
          "DATA_TRANSFER_INTERNAL_GBYTES": 0,
          "DATA_TRANSFER_EXTERNAL_GBYTES": 0,
          "PROXY_RESIDENTIAL_TRANSFER_GBYTES": 0,
          "PROXY_SERPS": 0
        },
        "consoleUrl": "https://console.apify.com/view/runs/dHGEPuVi9e5c9opK5",
        "actorName": "reddit-scraper-lite",
        "name": "Reddit Protected Community Check"
      },
      "runId": "dHGEPuVi9e5c9opK5"
    }
  ],
  [
    "c823b418cd815d46",
    {
      "hashCode": "c823b418cd815d46",
      "data": {
        "id": "LVBH6RXwTjhgHBjnt",
        "actId": "oAuCIx3ItNrs2okjQ",
        "stats": {
          "inputBodyLen": 481,
          "migrationCount": 0,
          "rebootCount": 0,
          "restartCount": 0,
          "resurrectCount": 0,
          "computeUnits": 0
        },
        "defaultKeyValueStoreId": "8vG8LdQrrQKzc8Mba",
        "defaultDatasetId": "P6rWQ3W0u1kRhgS0r",
        "defaultRequestQueueId": "BBIQBBPav2mxvWsbY",
        "pricingInfo": {
          "pricingModel": "PAY_PER_EVENT",
          "reasonForChange": "We are switching to Pay Per Event for a better pricing for our customers.",
          "startedAt": "2025-02-20T00:00:00.000Z",
          "minimalMaxTotalChargeUsd": null,
          "createdAt": "2025-02-13T10:52:56.554Z",
          "apifyMarginPercentage": 0.2,
          "notifiedAboutFutureChangeAt": "2025-02-13T10:53:21.733Z",
          "notifiedAboutChangeAt": "2025-02-20T02:39:19.462Z",
          "pricingPerEvent": {
            "actorChargeEvents": {
              "actor-start-gb": {
                "eventTitle": "Actor start per 1 GB",
                "eventDescription": "Flat fee for starting an Actor run for each 1 GB of memory.",
                "eventPriceUsd": 0.02
              },
              "result": {
                "eventTitle": "Result stored",
                "eventDescription": "Cost per result stored.",
                "eventPriceUsd": 0.004
              }
            }
          }
        },
        "chargedEventCounts": {
          "actor-start-gb": 0,
          "result": 0
        },
        "platformUsageBillingModel": "USER",
        "accountedChargedEventCounts": {
          "actor-start-gb": 0,
          "result": 0
        },
        "generalAccess": "FOLLOW_USER_SETTING",
        "buildNumber": "4.17.41",
        "usage": {
          "ACTOR_COMPUTE_UNITS": 0,
          "DATASET_READS": 0,
          "DATASET_WRITES": 0,
          "KEY_VALUE_STORE_READS": 0,
          "KEY_VALUE_STORE_WRITES": 1,
          "KEY_VALUE_STORE_LISTS": 0,
          "REQUEST_QUEUE_READS": 0,
          "REQUEST_QUEUE_WRITES": 0,
          "DATA_TRANSFER_INTERNAL_GBYTES": 0,
          "DATA_TRANSFER_EXTERNAL_GBYTES": 0,
          "PROXY_RESIDENTIAL_TRANSFER_GBYTES": 0,
          "PROXY_SERPS": 0
        },
        "usageTotalUsd": 0.00005,
        "usageUsd": {
          "ACTOR_COMPUTE_UNITS": 0,
          "DATASET_READS": 0,
          "DATASET_WRITES": 0,
          "KEY_VALUE_STORE_READS": 0,
          "KEY_VALUE_STORE_WRITES": 0.00005,
          "KEY_VALUE_STORE_LISTS": 0,
          "REQUEST_QUEUE_READS": 0,
          "REQUEST_QUEUE_WRITES": 0,
          "DATA_TRANSFER_INTERNAL_GBYTES": 0,
          "DATA_TRANSFER_EXTERNAL_GBYTES": 0,
          "PROXY_RESIDENTIAL_TRANSFER_GBYTES": 0,
          "PROXY_SERPS": 0
        },
        "consoleUrl": "https://console.apify.com/view/runs/LVBH6RXwTjhgHBjnt",
        "actorName": "reddit-scraper-lite",
        "name": "Reddit Popular Community Check"
      },
      "runId": "LVBH6RXwTjhgHBjnt"
    }
  ],
  [
    "8521dfdfe347dbac",
    {
      "hashCode": "8521dfdfe347dbac",
      "data": {
        "id": "czIAaG3zAGMsITRI0",
        "actId": "oAuCIx3ItNrs2okjQ",
        "stats": {
          "inputBodyLen": 670,
          "migrationCount": 0,
          "rebootCount": 0,
          "restartCount": 0,
          "resurrectCount": 0,
          "computeUnits": 0
        },
        "defaultKeyValueStoreId": "ACLLEKHBihaG9Sy0c",
        "defaultDatasetId": "UmYjnFPLPGZXqNDa3",
        "defaultRequestQueueId": "lLppaGQN7pCLhKh3W",
        "pricingInfo": {
          "pricingModel": "PAY_PER_EVENT",
          "reasonForChange": "We are switching to Pay Per Event for a better pricing for our customers.",
          "startedAt": "2025-02-20T00:00:00.000Z",
          "minimalMaxTotalChargeUsd": null,
          "createdAt": "2025-02-13T10:52:56.554Z",
          "apifyMarginPercentage": 0.2,
          "notifiedAboutFutureChangeAt": "2025-02-13T10:53:21.733Z",
          "notifiedAboutChangeAt": "2025-02-20T02:39:19.462Z",
          "pricingPerEvent": {
            "actorChargeEvents": {
              "actor-start-gb": {
                "eventTitle": "Actor start per 1 GB",
                "eventDescription": "Flat fee for starting an Actor run for each 1 GB of memory.",
                "eventPriceUsd": 0.02
              },
              "result": {
                "eventTitle": "Result stored",
                "eventDescription": "Cost per result stored.",
                "eventPriceUsd": 0.004
              }
            }
          }
        },
        "chargedEventCounts": {
          "actor-start-gb": 0,
          "result": 0
        },
        "platformUsageBillingModel": "USER",
        "accountedChargedEventCounts": {
          "actor-start-gb": 0,
          "result": 0
        },
        "generalAccess": "FOLLOW_USER_SETTING",
        "buildNumber": "4.17.41",
        "usage": {
          "ACTOR_COMPUTE_UNITS": 0,
          "DATASET_READS": 0,
          "DATASET_WRITES": 0,
          "KEY_VALUE_STORE_READS": 0,
          "KEY_VALUE_STORE_WRITES": 1,
          "KEY_VALUE_STORE_LISTS": 0,
          "REQUEST_QUEUE_READS": 0,
          "REQUEST_QUEUE_WRITES": 0,
          "DATA_TRANSFER_INTERNAL_GBYTES": 0,
          "DATA_TRANSFER_EXTERNAL_GBYTES": 0,
          "PROXY_RESIDENTIAL_TRANSFER_GBYTES": 0,
          "PROXY_SERPS": 0
        },
        "usageTotalUsd": 0.00005,
        "usageUsd": {
          "ACTOR_COMPUTE_UNITS": 0,
          "DATASET_READS": 0,
          "DATASET_WRITES": 0,
          "KEY_VALUE_STORE_READS": 0,
          "KEY_VALUE_STORE_WRITES": 0.00005,
          "KEY_VALUE_STORE_LISTS": 0,
          "REQUEST_QUEUE_READS": 0,
          "REQUEST_QUEUE_WRITES": 0,
          "DATA_TRANSFER_INTERNAL_GBYTES": 0,
          "DATA_TRANSFER_EXTERNAL_GBYTES": 0,
          "PROXY_RESIDENTIAL_TRANSFER_GBYTES": 0,
          "PROXY_SERPS": 0
        },
        "consoleUrl": "https://console.apify.com/view/runs/czIAaG3zAGMsITRI0",
        "actorName": "reddit-scraper-lite",
        "name": "Reddit User Check"
      },
      "runId": "czIAaG3zAGMsITRI0"
    }
  ],
  [
    "2a8a1b234c59895d",
    {
      "hashCode": "2a8a1b234c59895d",
      "data": {
        "id": "J3en4qPRSli8XE3Lu",
        "actId": "oAuCIx3ItNrs2okjQ",
        "stats": {
          "inputBodyLen": 570,
          "migrationCount": 0,
          "rebootCount": 0,
          "restartCount": 0,
          "resurrectCount": 0,
          "computeUnits": 0
        },
        "defaultKeyValueStoreId": "YkAvlZ8AXq4XGnVOI",
        "defaultDatasetId": "3nz4nORY3xPN714Qq",
        "defaultRequestQueueId": "hjPFcTERxHLj7Cr88",
        "pricingInfo": {
          "pricingModel": "PAY_PER_EVENT",
          "reasonForChange": "We are switching to Pay Per Event for a better pricing for our customers.",
          "startedAt": "2025-02-20T00:00:00.000Z",
          "minimalMaxTotalChargeUsd": null,
          "createdAt": "2025-02-13T10:52:56.554Z",
          "apifyMarginPercentage": 0.2,
          "notifiedAboutFutureChangeAt": "2025-02-13T10:53:21.733Z",
          "notifiedAboutChangeAt": "2025-02-20T02:39:19.462Z",
          "pricingPerEvent": {
            "actorChargeEvents": {
              "actor-start-gb": {
                "eventTitle": "Actor start per 1 GB",
                "eventDescription": "Flat fee for starting an Actor run for each 1 GB of memory.",
                "eventPriceUsd": 0.02
              },
              "result": {
                "eventTitle": "Result stored",
                "eventDescription": "Cost per result stored.",
                "eventPriceUsd": 0.004
              }
            }
          }
        },
        "chargedEventCounts": {
          "actor-start-gb": 0,
          "result": 0
        },
        "platformUsageBillingModel": "USER",
        "accountedChargedEventCounts": {
          "actor-start-gb": 0,
          "result": 0
        },
        "generalAccess": "FOLLOW_USER_SETTING",
        "buildNumber": "4.17.41",
        "usage": {
          "ACTOR_COMPUTE_UNITS": 0,
          "DATASET_READS": 0,
          "DATASET_WRITES": 0,
          "KEY_VALUE_STORE_READS": 0,
          "KEY_VALUE_STORE_WRITES": 1,
          "KEY_VALUE_STORE_LISTS": 0,
          "REQUEST_QUEUE_READS": 0,
          "REQUEST_QUEUE_WRITES": 0,
          "DATA_TRANSFER_INTERNAL_GBYTES": 0,
          "DATA_TRANSFER_EXTERNAL_GBYTES": 0,
          "PROXY_RESIDENTIAL_TRANSFER_GBYTES": 0,
          "PROXY_SERPS": 0
        },
        "usageTotalUsd": 0.00005,
        "usageUsd": {
          "ACTOR_COMPUTE_UNITS": 0,
          "DATASET_READS": 0,
          "DATASET_WRITES": 0,
          "KEY_VALUE_STORE_READS": 0,
          "KEY_VALUE_STORE_WRITES": 0.00005,
          "KEY_VALUE_STORE_LISTS": 0,
          "REQUEST_QUEUE_READS": 0,
          "REQUEST_QUEUE_WRITES": 0,
          "DATA_TRANSFER_INTERNAL_GBYTES": 0,
          "DATA_TRANSFER_EXTERNAL_GBYTES": 0,
          "PROXY_RESIDENTIAL_TRANSFER_GBYTES": 0,
          "PROXY_SERPS": 0
        },
        "consoleUrl": "https://console.apify.com/view/runs/J3en4qPRSli8XE3Lu",
        "actorName": "reddit-scraper-lite",
        "name": "Reddit Comment Check"
      },
      "runId": "J3en4qPRSli8XE3Lu"
    }
  ]
]